bpi.py
bpi-0.0.1.dist-info/WHEEL
bpi-0.0.1.dist-info/METADATA
bpi-0.0.1.dist-info/RECORD
