Metadata-Version: 2.1
Name: bpi
Version: 0.0.1
Summary: bot-programming-interface
Author: Olli Paloviita
Classifier: License :: OSI Approved :: MIT License
